rainbowtables/__init__.py
rainbowtables/directories.py
rainbowtables/errors.py
rainbowtables/insert.py
rainbowtables/search.py
rainbowtables-1.0.6.dist-info/LICENSE
rainbowtables-1.0.6.dist-info/METADATA
rainbowtables-1.0.6.dist-info/WHEEL
rainbowtables-1.0.6.dist-info/top_level.txt
rainbowtables-1.0.6.dist-info/RECORD
