Metadata-Version: 2.1
Name: rainbowtables
Version: 1.0.6
Summary: A python library allowing the user to create a rainbowtable.
Home-page: https://github.com/JustBennnn/rainbowtables
Author: JustBen
Author-email: justben009@gmail.com
License: MIT
Project-URL: Issue Tracker, https://github.com/JustBennnn/rainbowtables/issues
Keywords: rainbowtable
Platform: UNKNOWN
Classifier: Programming Language :: Python :: 3
Classifier: Development Status :: 5 - Production/Stable
Classifier: Intended Audience :: Developers
Classifier: License :: OSI Approved :: MIT License
Classifier: Operating System :: OS Independent
Classifier: Natural Language :: English
Classifier: Topic :: Software Development :: Libraries
Classifier: Topic :: Software Development :: Libraries :: Python Modules
Classifier: Topic :: Utilities
Requires-Python: >=3.7
License-File: LICENSE
Requires-Dist: sympy
